pyasista/__init__.py
pyasista/__version__.py
pyasista/models.py
pyasista-1.1.2.dist-info/METADATA
pyasista-1.1.2.dist-info/RECORD
pyasista-1.1.2.dist-info/WHEEL
pyasista-1.1.2.dist-info/top_level.txt
