Metadata-Version: 2.1
Name: pyasista
Version: 1.1.2
Summary: Arcelik Asista Smart Assistant AWS Lambda Python Library
Home-page: https://github.com/Arcelik/pyasista
Author: Arcelik Asista Team
License: Apache 2.0
Platform: UNKNOWN
Classifier: Development Status :: 4 - Beta
Classifier: Programming Language :: Python :: 3
Classifier: Programming Language :: Python :: 3.4
Classifier: Programming Language :: Python :: 3.5
Classifier: Programming Language :: Python :: 3.6
Classifier: Programming Language :: Python :: 3.7
Classifier: License :: OSI Approved :: Apache Software License
Classifier: Operating System :: OS Independent
Classifier: Intended Audience :: Developers
Requires-Python: >=3.4
